{
  "title":"例题",
  "example": [
    {
      "question": "<p >【例2】（C层次）在用自由落体运动验证机械能守恒定律时，某同学按照正确的操作得到如右图所示的纸带．其中<i>O</i>是起始点，<i>A</i>、<i>B</i>、<i>C</i>是打点计时器连续打下的3个点，该同学用毫米刻度尺测量<i>O</i>到<i>A</i>、<i>B</i>、<i>C</i>各点的距离，并记录在图中．已知打点计时器的电源周期为0.02s，重锤质量为1kg，当地的重力加速度<i>g</i>=9.8m/s<sup>2</sup>．</p><div class='imgback baguetteBoxOne center-pic' style='width: 400px'><img src='books/physics/images/pages/4-5-6.jpg' style='width: 380px'></div></p><p >　　（1）这三个数据中不符合有效数字读数要求的是_______段，应记作_______cm．</p><p >（2）该同学用<i>O</i><i>B</i>段重锤的运动来验证.先计算<i>A</i><i>C</i>段的平均速度作为<i>B</i>点的瞬时速度，得<i>υ</i><sub><i>B</i></sub>=_______，得重锤动能的增加量Δ<i>E</i><sub><i>k</i></sub>= _______；重力势能的减少量为Δ<i>E</i><sub><i>p</i></sub>=______（计算结果均保留3位有效数字）．由此得到结论：在误差允许的范围内，_____________________ .</p>",
      "answers": [],
      "correctAnswer": "",
      "details": "<p >【解析】（1）毫米刻度尺的最小刻度是毫米，读数要估读一位，到0.1mm．OC段没读到0.1mm而错误，应记作15.70cm．</p><p >（2）\\({\\upsilon _B} = \\frac{{{S_{OC}} - {S_{OA}}}}{{2T}} \\approx 1.55m/s\\)，Δ<i>E</i><sub><i>k</i></sub>=<i>E</i><sub><i>k</i></sub><sub><i>B</i></sub>=\\(\\dfrac{1}{2}m{\\upsilon _B}^2 \\approx 1.20J\\)；Δ<i>E</i><sub><i>p</i></sub>=<i>m</i><i>g</i><i>h</i><sub><i>O</i></sub><sub><i>B</i></sub><i>≈</i>1.22J．由此得到结论：在误差允许的范围内，重锤自由下落减少的重力势能等于动能的增加量.</p><p >【答案】（1）<i>O</i><i>C</i>，15.70；（2）1.22J，1.20J，重锤自由下落减少的重力势能等于动能的增加量.</p>",
      "summary": "【小结】1．用毫米刻度尺测量，若用cm作单位，必须估读至小数点后二位.2．某一时刻的瞬时速度借助某一段的平均速度等于中间时刻的速度的原理计算．"
    }
  ]
}
