{
  "title":"例题",
  "example": [
    {
      "question": "【例3】（B层次）已知太阳的质量约为2.0×10<sup>30</sup>kg，地球质量约为6.0×10<sup>24</sup>kg，太阳光从太阳射到地球需要约500s．求太阳和地球间的万有引力．",
      "answers": "",
      "correctAnswer": "2",
      "details": "【答案】太阳和地球之间的引力为 3.56×10<sup>20</sup>N．【解析】太阳与地球之间的距离<i>r</i>=<i>ct</i>=3.0×10<sup>8</sup>×500m=1.5×10<sup>11</sup>m太阳与地球之间的引力：\\(F = G\\dfrac{{{m_{\\rm{日}}}{m_{\\rm{地}}}}}{{{r^2}}} = 6.67 \\times {10^{ - 11}} \\times \\dfrac{{2.0 \\times {{10}^{30}} \\times 6.0 \\times {{10}^{24}}}}{{{{(1.5 \\times {{10}^{11}})}^2}}}{\\rm{N}}\\)=3.56×10<sup>20</sup>N",
      "summary": ""
    }
  ]
}